<?xml version="1.0" encoding="UTF-8"?>

<MAGUS-data CVS="$Revision: 1.13 $" Copyright="var." Jahr="1981-" MAGUS-Bild="13" MAGUS-Index="12" Maintainer="Malte Thoma" Name="Abenteuer" Region="X" Titel="Abenteuer" Version="1.0" offiziell="true">
 <Fertigkeiten>
  <Fertigkeit Anfangswert="15" Attribut="Gs" Erfolgswert="10" Lernkosten="60" Lernpunkte="3" Lernpunkte-Land="2" MaximalMitUnterweisung="18" Maximalwert="18" Name="Schlittschuhlaufen" Region="X" RegionZusatz="Smaskrifter">
   <Grund Typ="BN"/>
   <Standard Typ="As"/>
   <Standard Typ="Ba"/>
   <Standard Typ="BS"/>
   <Standard Typ="BW"/>
   <Standard Typ="dBe"/>
   <Standard Typ="De"/>
   <Standard Typ="Dr"/>
   <Standard Typ="Dt"/>
   <Standard Typ="eBe"/>
   <Standard Typ="Fi"/>
   <Standard Typ="gHx"/>
   <Standard Typ="Gl"/>
   <Standard Typ="Hä"/>
   <Standard Typ="Hj"/>
   <Standard Typ="Hl"/>
   <Standard Typ="Kd"/>
   <Standard Typ="Kr"/>
   <Standard Typ="Ma"/>
   <Standard Typ="Mg"/>
   <Standard Typ="MMa"/>
   <Standard Typ="Ny"/>
   <Standard Typ="Or"/>
   <Standard Typ="PC"/>
   <Standard Typ="PF"/>
   <Standard Typ="PK"/>
   <Standard Typ="PM"/>
   <Standard Typ="PT"/>
   <Standard Typ="PW"/>
   <Standard Typ="Ri"/>
   <Standard Typ="RiN"/>
   <Standard Typ="RiS"/>
   <Standard Typ="Ru"/>
   <Standard Typ="Sa"/>
   <Standard Typ="ScN"/>
   <Standard Typ="ScS"/>
   <Standard Typ="ScW"/>
   <Standard Typ="Se"/>
   <Standard Typ="sHx"/>
   <Standard Typ="Sk"/>
   <Standard Typ="Sö"/>
   <Standard Typ="Sp"/>
   <Standard Typ="Sr"/>
   <Standard Typ="Sw"/>
   <Standard Typ="tBe"/>
   <Standard Typ="Th"/>
   <Standard Typ="To"/>
   <Standard Typ="Tr"/>
   <Standard Typ="Tt"/>
   <Standard Typ="Wa"/>
   <Standard Typ="wHx"/>
   <Voraussetzungen Gw="21"/>
   <steigern_wie Fertigkeit="Bewegung"/>
   <EP-Typ KEP="true"/>
  </Fertigkeit>
  <Fertigkeit Name="Musizieren">
   <Zusätze Name="Cheng (Mundorgel)" Region="X" RegionZusatz="Unter der Sturmdrachen" Typ="Zupfinstrument"/>
  </Fertigkeit>
 </Fertigkeiten>
 <Berufe/>
 <Schriften/>
 <Sprachen>
  <Sprache Gruppe="10" Kosten="10" Maximalwert="20" Name="Ferangah" Region="X" RegionZusatz="Die schwarze Sphäre">
   <Schrift/>
  </Sprache>
 </Sprachen>
 <Typen/>
 <Rüstungen/>
 <Waffen/>
 <Waffen-Grundkenntnisse/>
 <Zauber>
  <Spruch AP="6" Grad="5" Lernkosten="2000" Material="Edelsteinstaub (10 GS)" Name="Die Wirklichkeit des Vertrauten ist stärker als die Augen" Region="X" RegionZusatz="Unter dem Sturmdrachen" Reichweite="30 m" Spruchrolle="true" Thaumagramm="Siegel" Typ="Geste" Wirkungsbereich="3x3x3 m" Wirkungsdauer="-" Wirkungsziel="Geist" Zauberdauer="20 s"/>
 </Zauber>
 <Zauberwerke/>
</MAGUS-data>
